xontrib/jedi.py
xontrib_jedi-0.1.1.dist-info/LICENSE
xontrib_jedi-0.1.1.dist-info/METADATA
xontrib_jedi-0.1.1.dist-info/WHEEL
xontrib_jedi-0.1.1.dist-info/RECORD
